[
  { "ID": "demo-specialty:守灯人:晨光记录员", "主职": "守灯人", "类型": "专长", "名称": "晨光记录员", "等级": "入门", "描述": "记录旅途中的重要路标，并把线索整理成简短笔记。" },
  { "ID": "demo-specialty:守灯人:暮色巡夜人", "主职": "守灯人", "类型": "专长", "名称": "暮色巡夜人", "等级": "进阶", "描述": "在光线昏暗时保持警觉，并负责最后一轮营地巡查。" },
  { "ID": "demo-specialty:林径使:苔痕向导", "主职": "林径使", "类型": "专长", "名称": "苔痕向导", "等级": "入门", "描述": "根据苔藓、风向和水声判断前进方向。" },
  { "ID": "demo-specialty:林径使:溪谷药师", "主职": "林径使", "类型": "专长", "名称": "溪谷药师", "等级": "进阶", "描述": "用常见草木制作气味清新的旅行药膏。" },
  { "ID": "demo-specialty:风帆客:云帆领航员", "主职": "风帆客", "类型": "专长", "名称": "云帆领航员", "等级": "入门", "描述": "从云层和旗帜的变化中提前读出天气。" },
  { "ID": "demo-specialty:风帆客:雷雨信使", "主职": "风帆客", "类型": "专长", "名称": "雷雨信使", "等级": "进阶", "描述": "即使风雨骤起，也能把一则短消息安全送达。" }
]
